ditto/matchers/__init__.py
ditto/matchers/class_task_matcher.py
ditto/matchers/python_call_task_matcher.py
ditto/resolvers/__init__.py
ditto/resolvers/ancestral_class_transformer_resolver.py
ditto/resolvers/class_transformer_resolver.py
ditto/resolvers/python_call_transformer_resolver.py
ditto/templates/__init__.py
ditto/templates/emr_hdi_check_cluster_template.py
ditto/templates/emr_hdi_template.py
ditto/transformers/__init__.py
ditto/transformers/copy_transformer.py
ditto/transformers/identity_transformer.py
ditto/transformers/emr/__init__.py
ditto/transformers/emr/emr_add_steps_op_transformer.py
ditto/transformers/emr/emr_create_job_flow_op_transformer.py
ditto/transformers/emr/emr_job_flow_sensor_transformer.py
ditto/transformers/emr/emr_step_sensor_transformer.py
ditto/transformers/emr/emr_terminate_job_flow_op_transformer.py
ditto/transformers/s3/__init__.py
ditto/transformers/s3/s3_key_sensor_adlsgen1_transformer.py
ditto/transformers/s3/s3_key_sensor_blob_transformer.py
ditto/transformers/subdag/__init__.py
ditto/transformers/subdag/check_cluster_subdag_transformer.py
airflow_ditto-0.0.1.2.dist-info/LICENSE
airflow_ditto-0.0.1.2.dist-info/METADATA
airflow_ditto-0.0.1.2.dist-info/WHEEL
airflow_ditto-0.0.1.2.dist-info/top_level.txt
airflow_ditto-0.0.1.2.dist-info/RECORD
