Metadata-Version: 2.1
Name: airflow-ditto
Version: 0.0.1.2
Summary: An airflow DAG transformation framework
Home-page: https://github.com/angadsingh/airflow-ditto
Author: Angad Singh
Author-email: angad.singh@trufactor.io
License: Apache Software License (http://www.apache.org/licenses/LICENSE-2.0)
Platform: UNKNOWN
Classifier: Programming Language :: Python :: 3
Classifier: License :: OSI Approved :: Apache Software License
Classifier: Operating System :: OS Independent
Requires-Python: >=3.7
Requires-Dist: deepdiff (==4.3.2)
Requires-Dist: networkx
Requires-Dist: apache-airflow (<=2.*,>=1.10.10)
Requires-Dist: matplotlib
Requires-Dist: airflow-hdinsight
Requires-Dist: boto3
Requires-Dist: parameterized
Requires-Dist: alchemy-mock
